kount/__init__.py
kount/client.py
kount/config.py
kount/inquiry.py
kount/request.py
kount/response.py
kount/settings.py
kount/test_inquiryex.py
kount/version.py
kount/resources/__init__.py
kount/resources/correct_key_cryp.py
kount/util/__init__.py
kount/util/a85.py
kount/util/address.py
kount/util/cartitem.py
kount/util/khash.py
kount/util/payment.py
uat_python_cicd-3.0.1.dist-info/LICENSE
uat_python_cicd-3.0.1.dist-info/METADATA
uat_python_cicd-3.0.1.dist-info/WHEEL
uat_python_cicd-3.0.1.dist-info/top_level.txt
uat_python_cicd-3.0.1.dist-info/RECORD
