Metadata-Version: 2.1
Name: uat-python-cicd
Version: 3.0.1
Summary: Test ci/cd
Home-page: https://gitlab.com/gitlab-ci-cd-pipeine/pythoncicdproject
Author: Kount
Author-email: sanjeev1992jha@gmail.com
License: Unknown
Keywords: python ci/cd,sanjeev python ci/cd
Platform: any
Classifier: Development Status :: 4 - Beta
Classifier: Intended Audience :: Developers
Classifier: Topic :: Software Development :: Build Tools
Classifier: Topic :: Internet :: WWW/HTTP
Classifier: Topic :: Software Development :: Libraries :: Python Modules
Classifier: License :: Other/Proprietary License
Classifier: Programming Language :: Python :: 2.7
Classifier: Programming Language :: Python :: 3.5
Classifier: Programming Language :: Python :: 3.6
Requires-Dist: requests (>=2.11.1)
Requires-Dist: mom (>=0.1.3) ; python_version < "3.0"
Requires-Dist: py2-ipaddress (>=3.4.1) ; python_version < "3.0"
Provides-Extra: dev
Requires-Dist: flake8 (>=2.5.0) ; extra == 'dev'
Requires-Dist: pytest (>=2.8.4) ; extra == 'dev'
Requires-Dist: pytest-cov (>=2.4.0) ; extra == 'dev'
Requires-Dist: pytest-profiling (>=1.1.1) ; extra == 'dev'
Requires-Dist: pylint (>=1.7.2) ; extra == 'dev'
Requires-Dist: pytest-html (>=1.14.2) ; extra == 'dev'
Requires-Dist: pytest-metadata (>=1.5.0) ; extra == 'dev'
Provides-Extra: test
Requires-Dist: pytest (>=2.8.4) ; extra == 'test'
Requires-Dist: pytest-cov (>=2.4.0) ; extra == 'test'
Requires-Dist: pytest-profiling (>=1.1.1) ; extra == 'test'
Requires-Dist: pytest-html (>=1.14.2) ; extra == 'test'
Requires-Dist: pytest-metadata (>=1.5.0) ; extra == 'test'
